{
	"info": {
		"_postman_id": "55b6a5b8-d1a7-42fd-9255-be3a9eda9115",
		"name": "api-manajemen-film",
		"schema": "https://schema.getpostman.com/json/collection/v2.1.0/collection.json",
		"_exporter_id": "47946402"
	},
	"item": [
		{
			"name": "cek-semua-movies",
			"request": {
				"method": "GET",
				"header": []
			},
			"response": []
		},
		{
			"name": "cek-salahsatu-movies",
			"request": {
				"method": "GET",
				"header": []
			},
			"response": []
		},
		{
			"name": "cek-id-yangtidakvalid",
			"request": {
				"method": "GET",
				"header": []
			},
			"response": []
		},
		{
			"name": "New Request",
			"request": {
				"method": "POST",
				"header": [],
				"body": {
					"mode": "raw",
					"raw": "{\r\n    \"title\": \"cukii\",\r\n    \"diector\": \"pemai\",\r\n    \"year\": \"2006\"\r\n}",
					"options": {
						"raw": {
							"language": "json"
						}
					}
				},
				"url": {
					"raw": "http://localhost:3000/movies",
					"protocol": "http",
					"host": [
						"localhost"
					],
					"port": "3000",
					"path": [
						"movies"
					]
				}
			},
			"response": []
		},
		{
			"name": "director-id",
			"request": {
				"method": "GET",
				"header": [],
				"url": {
					"raw": "http://localhost:3000/directors",
					"protocol": "http",
					"host": [
						"localhost"
					],
					"port": "3000",
					"path": [
						"directors"
					]
				}
			},
			"response": []
		},
		{
			"name": "cek semua director",
			"request": {
				"method": "GET",
				"header": []
			},
			"response": []
		},
		{
			"name": "post data",
			"request": {
				"method": "POST",
				"header": [],
				"body": {
					"mode": "raw",
					"raw": "{\r\n    \"id\": 7,\r\n    \"name\": \"mustopa\",\r\n    \"birthYear\": 1990\r\n}",
					"options": {
						"raw": {
							"language": "json"
						}
					}
				},
				"url": {
					"raw": "http://localhost:3000/directors",
					"protocol": "http",
					"host": [
						"localhost"
					],
					"port": "3000",
					"path": [
						"directors"
					]
				}
			},
			"response": []
		},
		{
			"name": "update",
			"request": {
				"method": "PUT",
				"header": [],
				"body": {
					"mode": "raw",
					"raw": "{\r\n    \"id\": 7,\r\n    \"name\": \"sorik\",\r\n    \"birthYear\": 2000\r\n}",
					"options": {
						"raw": {
							"language": "json"
						}
					}
				},
				"url": {
					"raw": "http://localhost:3000/directors/6",
					"protocol": "http",
					"host": [
						"localhost"
					],
					"port": "3000",
					"path": [
						"directors",
						"6"
					]
				}
			},
			"response": []
		},
		{
			"name": "hapus",
			"request": {
				"method": "DELETE",
				"header": [],
				"url": {
					"raw": "http://localhost:3000/directors/6",
					"protocol": "http",
					"host": [
						"localhost"
					],
					"port": "3000",
					"path": [
						"directors",
						"6"
					]
				}
			},
			"response": []
		}
	]
}